megham/__init__.py
megham/mds.py
megham/transform.py
megham/utils.py
megham-1.4.0.dist-info/licenses/LICENSE
megham-1.4.0.dist-info/METADATA
megham-1.4.0.dist-info/WHEEL
megham-1.4.0.dist-info/top_level.txt
megham-1.4.0.dist-info/RECORD
