Metadata-Version: 2.4
Name: megham
Version: 1.4.0
Summary: Tools for working with point clouds
Author: Saianeesh Keshav Haridas
License: GPLv3
Keywords: point cloud,affine,rotations,mds,multidimensional scaling,point set registration,cpd,coherent point drift,mpd,guassian mixture model
Classifier: Programming Language :: Python
Requires-Python: >=3.8
License-File: LICENSE
Requires-Dist: numpy
Requires-Dist: scipy
Requires-Dist: scikit-learn
Provides-Extra: docs
Requires-Dist: mkdocs; extra == "docs"
Requires-Dist: mkdocs-material; extra == "docs"
Requires-Dist: mkdocstrings[python]; extra == "docs"
Requires-Dist: mkdocs-gen-files; extra == "docs"
Requires-Dist: mkdocs-literate-nav; extra == "docs"
Requires-Dist: mkdocs-homepage-copier; extra == "docs"
Dynamic: license-file
